uiauto_dev/__init__.py
uiauto_dev/__main__.py
uiauto_dev/app.py
uiauto_dev/appium_proxy.py
uiauto_dev/case.py
uiauto_dev/cli.py
uiauto_dev/command_proxy.py
uiauto_dev/command_types.py
uiauto_dev/driver/android.py
uiauto_dev/driver/appium.py
uiauto_dev/driver/base_driver.py
uiauto_dev/driver/ios.py
uiauto_dev/driver/mock.py
uiauto_dev/driver/udt/appium-uiautomator2-v5.12.4-light.apk
uiauto_dev/driver/udt/udt.py
uiauto_dev/exceptions.py
uiauto_dev/model.py
uiauto_dev/provider.py
uiauto_dev/router/device.py
uiauto_dev/router/xml.py
uiauto_dev/static/demo.html
uiauto_dev/utils/common.py
uiauto_dev/utils/exceptions.py
uiauto_dev/utils/usbmux.py
uiauto_dev-0.3.2.dist-info/LICENSE
uiauto_dev-0.3.2.dist-info/METADATA
uiauto_dev-0.3.2.dist-info/WHEEL
uiauto_dev-0.3.2.dist-info/entry_points.txt
uiauto_dev-0.3.2.dist-info/RECORD
