Metadata-Version: 2.1
Name: uiauto-dev
Version: 0.3.2
Summary: Mobile UI Automation, include UI hierarchy inspector, script recorder
Home-page: https://uiauto.dev
License: MIT
Author: codeskyblue
Author-email: codeskyblue@gmail.com
Requires-Python: >=3.8,<4.0
Classifier: License :: OSI Approved :: MIT License
Classifier: Programming Language :: Python :: 3
Classifier: Programming Language :: Python :: 3.8
Classifier: Programming Language :: Python :: 3.9
Classifier: Programming Language :: Python :: 3.10
Classifier: Programming Language :: Python :: 3.11
Classifier: Programming Language :: Python :: 3.12
Provides-Extra: appium
Requires-Dist: adbutils (>=2.4.1,<3.0.0)
Requires-Dist: appium-python-client (>=4.0.0,<5.0.0) ; extra == "appium"
Requires-Dist: click (>=8.1.7,<9.0.0)
Requires-Dist: construct
Requires-Dist: fastapi[all] (>=0.109.2,<0.110.0)
Requires-Dist: httpretty (>=1.1.4,<2.0.0)
Requires-Dist: lxml
Requires-Dist: pillow
Requires-Dist: pygments (>=2)
Requires-Dist: uvicorn[standard] (>=0.27.1,<0.28.0)
